mkdocs_data_plugin/__init__.py
mkdocs_data_plugin/plugin.py
mkdocs_data_plugin-0.2.0.dist-info/METADATA
mkdocs_data_plugin-0.2.0.dist-info/WHEEL
mkdocs_data_plugin-0.2.0.dist-info/entry_points.txt
mkdocs_data_plugin-0.2.0.dist-info/licenses/LICENSE
mkdocs_data_plugin-0.2.0.dist-info/RECORD
